stpp_tplot/__init__.py
stpp_tplot/plot_function.py
stpp_tplot-0.1.3.dist-info/licenses/LICENSE
stpp_tplot-0.1.3.dist-info/METADATA
stpp_tplot-0.1.3.dist-info/WHEEL
stpp_tplot-0.1.3.dist-info/top_level.txt
stpp_tplot-0.1.3.dist-info/RECORD
