Metadata-Version: 2.4
Name: stpp_tplot
Version: 0.1.3
Summary: Simple time series plotting library based on pyspedas and matplotlib.
Home-page: https://github.com/JackKTachi/stpp_tplot
Author: Kohki Tachi
Author-email: ktachiresearch@gmail.com
License: MIT
Classifier: Programming Language :: Python :: 3
Classifier: License :: OSI Approved :: MIT License
Classifier: Operating System :: OS Independent
Classifier: Intended Audience :: Science/Research
Classifier: Topic :: Scientific/Engineering :: Visualization
License-File: LICENSE
Requires-Dist: matplotlib
Requires-Dist: pyspedas
Requires-Dist: pytz
Requires-Dist: numpy
Dynamic: author
Dynamic: author-email
Dynamic: classifier
Dynamic: description
Dynamic: description-content-type
Dynamic: home-page
Dynamic: license
Dynamic: license-file
Dynamic: requires-dist
Dynamic: summary
